orangeqs/sphinx/__init__.py
orangeqs/sphinx/_static_version.py
orangeqs/sphinx/_version.py
orangeqs/sphinx/autodoc2/__init__.py
orangeqs/sphinx/autodoc2/numpydoc.py
orangeqs/sphinx/theme/__init__.py
orangeqs/sphinx/theme/theme.toml
orangeqs/sphinx/theme/static/OQS_docs.svg
orangeqs/sphinx/theme/static/OrangeQS-logo_tagline.svg
orangeqs/sphinx/theme/static/OrangeQS-logo_tagline_diapositive.svg
orangeqs/sphinx/theme/static/OrangeQS_logo_no_text.svg
orangeqs/sphinx/theme/static/orangeqs.css
orangeqs_sphinx_extensions-0.1.2.dist-info/licenses/LICENSE.txt
orangeqs_sphinx_extensions-0.1.2.dist-info/METADATA
orangeqs_sphinx_extensions-0.1.2.dist-info/WHEEL
orangeqs_sphinx_extensions-0.1.2.dist-info/entry_points.txt
orangeqs_sphinx_extensions-0.1.2.dist-info/top_level.txt
orangeqs_sphinx_extensions-0.1.2.dist-info/RECORD
