Metadata-Version: 2.4
Name: orangeqs-sphinx-extensions
Version: 0.1.2
Summary: Sphinx theme and custom extensions used internally by Orange Quantum Systems
Author-email: Orange Quantum Systems <support@orangeqs.com>
License: Copyright 2024 Orange Quantum Systems Operational B.V.
Project-URL: repository, https://code.orangeqs.com/opensource/oqs-sphinx-theme
Classifier: Framework :: Sphinx :: Theme
Classifier: Programming Language :: Python :: 3 :: Only
Classifier: Topic :: Documentation
Classifier: Topic :: Documentation :: Sphinx
Requires-Python: >=3.9
License-File: LICENSE.txt
Requires-Dist: pydata-sphinx-theme
Provides-Extra: autodoc2
Requires-Dist: sphinx-autodoc2; extra == "autodoc2"
Requires-Dist: numpydoc; extra == "autodoc2"
Dynamic: license-file
